voyager_mcp/__init__.py
voyager_mcp/server.py
voyager_mcp-0.1.1.dist-info/METADATA
voyager_mcp-0.1.1.dist-info/WHEEL
voyager_mcp-0.1.1.dist-info/entry_points.txt
voyager_mcp-0.1.1.dist-info/licenses/LICENSE
voyager_mcp-0.1.1.dist-info/RECORD
