Metadata-Version: 2.4
Name: voyager-mcp
Version: 0.1.1
Summary: A Voyager-inspired MCP server for local CLI skill library
Project-URL: repository, https://github.com/changjonathanc/voyager-mcp
Author-email: Jonathan Chang <changjonathanc@users.noreply.github.com>
License-File: LICENSE
Requires-Python: >=3.10
Requires-Dist: mcp>=1.10.1
